turtles3D.py
turtles3D-0.9.1.dist-info/LICENSE
turtles3D-0.9.1.dist-info/METADATA
turtles3D-0.9.1.dist-info/WHEEL
turtles3D-0.9.1.dist-info/top_level.txt
turtles3D-0.9.1.dist-info/RECORD
