Metadata-Version: 2.1
Name: turtles3D
Version: 0.9.1
Summary: A 3D extension built on the turtle library
Author: Eric Nelson
Project-URL: Homepage, https://github.com/neric89/3DTurtles
Keywords: turtle,3D,drawing
Classifier: Programming Language :: Python :: 3
Classifier: License :: OSI Approved :: MIT License
Classifier: Operating System :: OS Independent
Requires-Python: >=3.6
License-File: LICENSE
Requires-Dist: numpy
Requires-Dist: typing
Requires-Dist: future
